model_store_interface/README.md
model_store_interface/__init__.py
model_store_interface/aggregator.py
model_store_interface/cli.py
model_store_interface/default_create_functions.py
model_store_interface/local_learner.py
model_store_interface/mlflow_interface.py
model_store_interface/py.typed
model_store_interface/templates.py
model_store_interface/src/utils.py
model_store_interface/templates/client_app_template.py
model_store_interface/templates/example_template.py
model_store_interface/templates/readme_template.md
model_store_interface/templates/server_app_template.py
model_store_interface/templates/utils_template.py
model_store_interface-0.5.0.dist-info/METADATA
model_store_interface-0.5.0.dist-info/WHEEL
model_store_interface-0.5.0.dist-info/entry_points.txt
model_store_interface-0.5.0.dist-info/licenses/LICENSE
model_store_interface-0.5.0.dist-info/RECORD
