Metadata-Version: 2.4
Name: model-store-interface
Version: 0.5.0
Summary: This package contains the core components and protocols for creating, managing, and registering federated learning models using MLflow. It provides utilities for defining local learners, aggregation strategies, and integrating them with MLflow for tracking and deployment.
Author-email: ceresale <alessandro.ceresi@upm.es>
License-File: LICENSE
Requires-Python: <3.12,>=3.11
Requires-Dist: flwr==1.9
Requires-Dist: mlflow-skinny>=2.19.0
Requires-Dist: pandas>=2.2.3
Provides-Extra: edge
Requires-Dist: torch==2.5.1; extra == 'edge'
